iron_toolbox/aws_functions.py
iron_toolbox/domo_functions.py
iron_toolbox/iron_functions.py
iron_toolbox/mongo_functions.py
iron_toolbox/sftp_functions.py
iron_toolbox-1.6.dist-info/licenses/LICENSE.txt
iron_toolbox-1.6.dist-info/METADATA
iron_toolbox-1.6.dist-info/WHEEL
iron_toolbox-1.6.dist-info/top_level.txt
iron_toolbox-1.6.dist-info/RECORD
