Metadata-Version: 2.4
Name: iron_toolbox
Version: 1.6
Summary: Functions to be used by Iron Data Analytics Team
Home-page: https://github.com/IronTrainers/iron_data_toolbox
Download-URL: https://github.com/IronTrainers/iron_data_toolbox/archive/refs/tags/iron_data_toolboox.tar.gz
Author: Luciano Siqueira
Author-email: lucianosiqueira@iron.fit
License: MIT
Project-URL: Bug Tracker, https://github.com/IronTrainers/iron_data_toolbox/issues
Keywords: python,mongodb,aws,domo,iron_toolbox
License-File: LICENSE.txt
Requires-Dist: DateTime==5.1
Requires-Dist: duckdb==0.7.1
Requires-Dist: fsspec==2022.7.1
Requires-Dist: paramiko
Requires-Dist: pydomo==0.3.0.9
Requires-Dist: pymongo==4.6.3
Requires-Dist: s3fs==2022.7.1
Requires-Dist: tqdm==4.65.0
Requires-Dist: Unidecode==1.3.6
Requires-Dist: pysftp==0.2.9
Dynamic: author
Dynamic: author-email
Dynamic: description
Dynamic: description-content-type
Dynamic: download-url
Dynamic: home-page
Dynamic: keywords
Dynamic: license
Dynamic: license-file
Dynamic: project-url
Dynamic: requires-dist
Dynamic: summary
